setup.py
py_upyun.egg-info/PKG-INFO
py_upyun.egg-info/SOURCES.txt
py_upyun.egg-info/dependency_links.txt
py_upyun.egg-info/requires.txt
py_upyun.egg-info/top_level.txt
youpai/__init__.py
youpai/configure.py
youpai/downloader.py
youpai/exception.py
youpai/tool.py
youpai/upyun.py
youpai/upyunclient.py