Metadata-Version: 1.1
Name: py-upyun
Version: 0.1.2
Summary: Youpai Usage API
Home-page: UNKNOWN
Author: zixuan zhang
Author-email: zixuan.zhang.victor@gmail.com
License: UNKNOWN
Keywords: youpai,upyun,cloud
Platform: UNKNOWN
Classifier: Environment :: Console
Classifier: Intended Audience :: Developers
Classifier: Operating System :: OS Independent
Classifier: Programming Language :: Python
